setup.py
eye_keyboard/__init__.py
eye_keyboard/app.py
eye_keyboard/calibration.py
eye_keyboard/eye_tracker.py
eye_keyboard/keyboard.py
eye_keyboard.egg-info/PKG-INFO
eye_keyboard.egg-info/SOURCES.txt
eye_keyboard.egg-info/dependency_links.txt
eye_keyboard.egg-info/entry_points.txt
eye_keyboard.egg-info/not-zip-safe
eye_keyboard.egg-info/requires.txt
eye_keyboard.egg-info/top_level.txt