Metadata-Version: 1.1
Name: eye-keyboard
Version: 0.0.1
Summary: Extending webcam-eyetracker for use a keyboard with pupils
Home-page: https://github.com/emanuelvianna/eye-keyboard
Author: Emanuel Vianna
Author-email: emanuelvianna@gmail.com
License: GPL
Keywords: webcam avc eye pupils keyboard tracker
Platform: any
Classifier: Development Status :: 2 - Pre-Alpha
Classifier: License :: OSI Approved :: GNU General Public License (GPL)
Classifier: Programming Language :: Python
Classifier: Topic :: Adaptive Technologies
